{
  "ComponentIndexes": {},
  "ControlUniqueGuids": {},
  "ControlUniqueIds": {
    "8d4b12e1-8250-4eaf-863d-405bbb32f47b": 180,
    "9771dc74-bce8-4b90-87e7-e57d8f02d4af": 179,
    "AddAppliancesForm": 100,
    "AddIngredientsForm": 74,
    "AddPicture1": 115,
    "App": 1,
    "Appliance_Image_DataCard1": 111,
    "Body1_1": 161,
    "Button1_10": 40,
    "Button1_11": 39,
    "Button1_9": 42,
    "Button2": 178,
    "Button3": 153,
    "Button3_1": 143,
    "Button3_2": 68,
    "Button4": 16,
    "Button4_1": 21,
    "Button4_2": 24,
    "Button4_3": 29,
    "Button4_4": 33,
    "Button4_5": 36,
    "Checkbox1": 58,
    "Checkbox1_1": 60,
    "Checkbox1_2": 61,
    "Checkbox1_3": 59,
    "Checkbox1_4": 62,
    "Checkbox1_5": 63,
    "Checkbox1_6": 65,
    "Checkbox1_7": 66,
    "Checkbox1_8": 67,
    "Circle1": 17,
    "Circle1_1": 20,
    "Circle1_2": 25,
    "Circle1_3": 28,
    "Circle1_4": 32,
    "Circle1_5": 37,
    "Container1": 170,
    "Container2": 134,
    "Container2_1": 164,
    "Container2_2": 69,
    "Container2_3": 38,
    "Container3": 152,
    "Container4": 142,
    "Container5": 52,
    "Container6": 56,
    "Container7": 125,
    "Cooking Method(s)_DataCard1": 117,
    "DataCardKey1": 108,
    "DataCardKey2": 113,
    "DataCardKey3": 119,
    "DataCardKey6": 82,
    "DataCardKey7": 87,
    "DataCardKey8": 92,
    "DataCardKey9": 97,
    "DataCardValue1": 109,
    "DataCardValue2": 120,
    "DataCardValue6": 83,
    "DataCardValue7": 88,
    "DataCardValue8": 93,
    "DataCardValue9": 98,
    "EditForm1": 105,
    "EditForm2": 79,
    "ErrorMessage1": 110,
    "ErrorMessage2": 116,
    "ErrorMessage3": 121,
    "ErrorMessage6": 84,
    "ErrorMessage7": 89,
    "ErrorMessage8": 94,
    "ErrorMessage9": 99,
    "Expiry_DataCard2": 85,
    "Gallery1": 126,
    "Gallery1_1": 154,
    "Gallery2": 144,
    "galleryTemplate1": 127,
    "galleryTemplate1_1": 155,
    "galleryTemplate2": 145,
    "Group2": 47,
    "Group4": 138,
    "Group4_1": 45,
    "Group4_2": 168,
    "Group4_3": 73,
    "Group7": 48,
    "Home": 122,
    "Host": 3,
    "Icon1": 137,
    "Icon1_1": 167,
    "Icon1_2": 72,
    "Icon1_3": 43,
    "Icon2": 135,
    "Icon2_1": 165,
    "Icon2_2": 70,
    "Icon2_3": 41,
    "Icon3": 136,
    "Icon3_1": 166,
    "Icon3_2": 71,
    "Icon3_3": 44,
    "Icon4": 175,
    "Icon5": 173,
    "Icon6": 176,
    "Icon7": 8,
    "Icon8": 160,
    "IconAccept1": 104,
    "IconAccept2": 78,
    "IconCancel1": 102,
    "IconCancel2": 76,
    "Image1": 9,
    "Image10": 114,
    "Image2": 129,
    "Image5": 171,
    "Image5_1": 5,
    "Image9": 147,
    "Kitchen": 139,
    "Label1": 123,
    "Label1_1": 124,
    "Label1_2": 51,
    "Label1_3": 140,
    "Label1_4": 141,
    "Label10": 11,
    "Label11": 12,
    "Label12": 15,
    "Label12_1": 19,
    "Label12_2": 23,
    "Label12_3": 27,
    "Label12_4": 31,
    "Label12_5": 35,
    "Label2": 163,
    "Label2_1": 151,
    "Label3": 53,
    "Label4": 177,
    "Label5": 54,
    "Label6": 55,
    "Label7": 57,
    "Label7_1": 64,
    "Label8": 7,
    "Label9": 10,
    "LblAppName1": 103,
    "LblAppName2": 77,
    "Login": 169,
    "NextArrow1": 132,
    "NextArrow3": 148,
    "NextArrow4_1": 157,
    "password_input": 174,
    "Preference": 4,
    "Quantity_DataCard2": 90,
    "Rectangle1": 128,
    "Rectangle2": 6,
    "Rectangle3": 13,
    "Rectangle4_1": 156,
    "Rectangle5": 14,
    "Rectangle5_1": 18,
    "Rectangle5_2": 22,
    "Rectangle5_3": 26,
    "Rectangle5_4": 30,
    "Rectangle5_5": 34,
    "Rectangle6": 146,
    "RectQuickActionBar1": 101,
    "RectQuickActionBar2": 75,
    "Separator1": 133,
    "Separator3": 150,
    "Separator4_1": 162,
    "Settings": 50,
    "StarVisible1": 107,
    "StarVisible2": 112,
    "StarVisible3": 118,
    "StarVisible6": 81,
    "StarVisible7": 86,
    "StarVisible8": 91,
    "StarVisible9": 96,
    "Subtitle1": 131,
    "Subtitle3_1": 159,
    "Test_7F478737223C4B69": 2,
    "Title_DataCard1": 106,
    "Title_DataCard2": 80,
    "Title1": 130,
    "Title4_1": 158,
    "Title7": 149,
    "Units_DataCard2": 95,
    "username_input": 172,
    "Wheat": 49,
    "Wheat_1": 46
  },
  "DoesTestStepsMetadataExist": true,
  "FunctionParamsInvariantScripts": {},
  "FunctionParamsInvariantScriptsOnInstances": {},
  "HeaderLastSavedDateTimeUTC": "05/14/2024 01:17:17",
  "IsLegacyComponentAllowGlobalScopeCase": false,
  "LocalConnectionIDReferences": {
    "42e37ee2-cf27-43cf-957a-f88c367d433c": "\"/providers/microsoft.powerapps/apis/shared_sharepointonline/connections/d0ba32a2136242708a8a223fa973af13\"",
    "73c82abf-33bd-4e78-9731-4cc6d8f34076": "\"/providers/microsoft.powerapps/apis/shared_sharepointonline/connections/d0ba32a2136242708a8a223fa973af13\"",
    "bebc8f8c-506f-4e55-a7e6-08f3956f308b": "\"/providers/microsoft.powerapps/apis/shared_office365users/connections/49a56132a3c24b0abb14069bdf921751\"",
    "e7b3922e-9165-4d2b-99a7-08850a5372fb": "\"/providers/microsoft.powerapps/apis/shared_office365/connections/ecee5973e2a64c9a8b95d479e981a17b\""
  },
  "LocalDatabaseReferencesAsEmpty": true,
  "LocalResourceFileNames": {
    "615-6151019_white-rounded-rectangle-png-squircle-shape-transparent-png": "0001.png",
    "blank-profile-picture-973460_640": "0002.png",
    "image2706832": "0003.png",
    "image2706833": "0004.png",
    "image2706834": "0005.png",
    "image2706835": "0006.png",
    "image2706836": "0007.png",
    "image2706851": "0008.png",
    "image2706933": "0009.png",
    "image2706935": "0010.png",
    "image2706941": "0011.png",
    "png-clipart-computer-icons-rectangle-graphics-software-rounded-polygon-black-thumbnail": "0012.png",
    "Screenshot 2024-05-12 122449": "0013.png",
    "wallpapersden.com_blue-violet-minimal-gradient_7680x4320": "0014.jpg",
    "wearenotthesame-v0-amxhlh6ih5hc1": "0015.jpeg"
  },
  "LocalResourceRootPaths": {
    "615-6151019_white-rounded-rectangle-png-squircle-shape-transparent-png": "https://docserverpwaprodseau.blob.core.windows.net/61486d5b-017f-479f-8a47-174bd52dd6f4-1/resource/Assets0Images00001.png?skoid=58690ece-ec83-4ce2-9ce8-883d4d6a54ee&sktid=975f013f-7f24-47e8-a7d3-abc4752bf346&skt=2024-05-14T01%3A15%3A10Z&ske=2024-05-15T01%3A30%3A10Z&sks=b&skv=2022-11-02&sv=2022-11-02&spr=https&se=2024-05-15T01%3A30%3A10Z&sr=b&sp=r&sig=Mycwzx0r5RFn8E35mC4961A7Ibn34PdeXfTFwhak3is%3D",
    "blank-profile-picture-973460_640": "https://docserverpwaprodseau.blob.core.windows.net/61486d5b-017f-479f-8a47-174bd52dd6f4-1/resource/Assets0Images00002.png?skoid=58690ece-ec83-4ce2-9ce8-883d4d6a54ee&sktid=975f013f-7f24-47e8-a7d3-abc4752bf346&skt=2024-05-14T01%3A15%3A10Z&ske=2024-05-15T01%3A30%3A10Z&sks=b&skv=2022-11-02&sv=2022-11-02&spr=https&se=2024-05-15T01%3A30%3A10Z&sr=b&sp=r&sig=t0xKv6jIqAIPKeM%2B52UTrUcHDVN7FePNyQwtVw0qit4%3D",
    "image2706832": "https://docserverpwaprodseau.blob.core.windows.net/61486d5b-017f-479f-8a47-174bd52dd6f4-1/resource/Assets0Images00003.png?skoid=58690ece-ec83-4ce2-9ce8-883d4d6a54ee&sktid=975f013f-7f24-47e8-a7d3-abc4752bf346&skt=2024-05-14T01%3A15%3A10Z&ske=2024-05-15T01%3A30%3A10Z&sks=b&skv=2022-11-02&sv=2022-11-02&spr=https&se=2024-05-15T01%3A30%3A10Z&sr=b&sp=r&sig=1plyQim0DFcSQtM8w6lrCQpTCKbSVPLpfj166%2FReU%2BQ%3D",
    "image2706833": "https://docserverpwaprodseau.blob.core.windows.net/61486d5b-017f-479f-8a47-174bd52dd6f4-1/resource/Assets0Images00004.png?skoid=58690ece-ec83-4ce2-9ce8-883d4d6a54ee&sktid=975f013f-7f24-47e8-a7d3-abc4752bf346&skt=2024-05-14T01%3A15%3A10Z&ske=2024-05-15T01%3A30%3A10Z&sks=b&skv=2022-11-02&sv=2022-11-02&spr=https&se=2024-05-15T01%3A30%3A10Z&sr=b&sp=r&sig=3Xcg3%2BL%2B4D77mCUz%2BdRgvgmQNC4W1ykGDxQia8qOe3s%3D",
    "image2706834": "https://docserverpwaprodseau.blob.core.windows.net/61486d5b-017f-479f-8a47-174bd52dd6f4-1/resource/Assets0Images00005.png?skoid=58690ece-ec83-4ce2-9ce8-883d4d6a54ee&sktid=975f013f-7f24-47e8-a7d3-abc4752bf346&skt=2024-05-14T01%3A15%3A10Z&ske=2024-05-15T01%3A30%3A10Z&sks=b&skv=2022-11-02&sv=2022-11-02&spr=https&se=2024-05-15T01%3A30%3A10Z&sr=b&sp=r&sig=KnBTcPfJRZ%2FxDsE52FSgdGvsncCEgG3Lcg3iskNZLhs%3D",
    "image2706835": "https://docserverpwaprodseau.blob.core.windows.net/61486d5b-017f-479f-8a47-174bd52dd6f4-1/resource/Assets0Images00006.png?skoid=58690ece-ec83-4ce2-9ce8-883d4d6a54ee&sktid=975f013f-7f24-47e8-a7d3-abc4752bf346&skt=2024-05-14T01%3A15%3A10Z&ske=2024-05-15T01%3A30%3A10Z&sks=b&skv=2022-11-02&sv=2022-11-02&spr=https&se=2024-05-15T01%3A30%3A10Z&sr=b&sp=r&sig=yNY%2Bjz3wuJwy%2F7SkKtpKUsLPhTvSfThlM4qxclQRhxw%3D",
    "image2706836": "https://docserverpwaprodseau.blob.core.windows.net/61486d5b-017f-479f-8a47-174bd52dd6f4-1/resource/Assets0Images00007.png?skoid=58690ece-ec83-4ce2-9ce8-883d4d6a54ee&sktid=975f013f-7f24-47e8-a7d3-abc4752bf346&skt=2024-05-14T01%3A15%3A10Z&ske=2024-05-15T01%3A30%3A10Z&sks=b&skv=2022-11-02&sv=2022-11-02&spr=https&se=2024-05-15T01%3A30%3A10Z&sr=b&sp=r&sig=7YATxuK2FKkzY45iNXt9Jc5wp4DBS5%2F%2Bbi4r0HbB214%3D",
    "image2706851": "https://docserverpwaprodseau.blob.core.windows.net/61486d5b-017f-479f-8a47-174bd52dd6f4-1/resource/Assets0Images00008.png?skoid=58690ece-ec83-4ce2-9ce8-883d4d6a54ee&sktid=975f013f-7f24-47e8-a7d3-abc4752bf346&skt=2024-05-14T01%3A15%3A10Z&ske=2024-05-15T01%3A30%3A10Z&sks=b&skv=2022-11-02&sv=2022-11-02&spr=https&se=2024-05-15T01%3A30%3A10Z&sr=b&sp=r&sig=y5f%2FgsmrF9CrvpB5AgONuK%2FVI7SSv0ayLnRtlF9jOOE%3D",
    "image2706933": "https://docserverpwaprodseau.blob.core.windows.net/61486d5b-017f-479f-8a47-174bd52dd6f4-1/resource/Assets0Images00009.png?skoid=58690ece-ec83-4ce2-9ce8-883d4d6a54ee&sktid=975f013f-7f24-47e8-a7d3-abc4752bf346&skt=2024-05-14T01%3A15%3A10Z&ske=2024-05-15T01%3A30%3A10Z&sks=b&skv=2022-11-02&sv=2022-11-02&spr=https&se=2024-05-15T01%3A30%3A10Z&sr=b&sp=r&sig=TPV7tYajxHASDvQfp93FAr16Yc%2FskoIvPWoxxujaWN4%3D",
    "image2706935": "https://docserverpwaprodseau.blob.core.windows.net/61486d5b-017f-479f-8a47-174bd52dd6f4-1/resource/Assets0Images00010.png?skoid=58690ece-ec83-4ce2-9ce8-883d4d6a54ee&sktid=975f013f-7f24-47e8-a7d3-abc4752bf346&skt=2024-05-14T01%3A15%3A10Z&ske=2024-05-15T01%3A30%3A10Z&sks=b&skv=2022-11-02&sv=2022-11-02&spr=https&se=2024-05-15T01%3A30%3A10Z&sr=b&sp=r&sig=InyiMi6bh3NX1OqBg4aFCL3hYRZ6p5%2BqSWjLAz3GwnA%3D",
    "image2706941": "https://docserverpwaprodseau.blob.core.windows.net/61486d5b-017f-479f-8a47-174bd52dd6f4-1/resource/Assets0Images00011.png?skoid=58690ece-ec83-4ce2-9ce8-883d4d6a54ee&sktid=975f013f-7f24-47e8-a7d3-abc4752bf346&skt=2024-05-14T01%3A15%3A10Z&ske=2024-05-15T01%3A30%3A10Z&sks=b&skv=2022-11-02&sv=2022-11-02&spr=https&se=2024-05-15T01%3A30%3A10Z&sr=b&sp=r&sig=DbeV%2Fy3BO8qWilxi4OUwCcDjejj1GhOq09JdKippIMc%3D",
    "png-clipart-computer-icons-rectangle-graphics-software-rounded-polygon-black-thumbnail": "https://docserverpwaprodseau.blob.core.windows.net/61486d5b-017f-479f-8a47-174bd52dd6f4-1/resource/Assets0Images00012.png?skoid=58690ece-ec83-4ce2-9ce8-883d4d6a54ee&sktid=975f013f-7f24-47e8-a7d3-abc4752bf346&skt=2024-05-14T01%3A15%3A10Z&ske=2024-05-15T01%3A30%3A10Z&sks=b&skv=2022-11-02&sv=2022-11-02&spr=https&se=2024-05-15T01%3A30%3A10Z&sr=b&sp=r&sig=WCXekgBz%2BxPrTM1mB1jZpHmbARj%2FeKT3%2FHv5F9PupgE%3D",
    "Screenshot 2024-05-12 122449": "https://docserverpwaprodseau.blob.core.windows.net/61486d5b-017f-479f-8a47-174bd52dd6f4-1/resource/Assets0Images00013.png?skoid=58690ece-ec83-4ce2-9ce8-883d4d6a54ee&sktid=975f013f-7f24-47e8-a7d3-abc4752bf346&skt=2024-05-14T01%3A15%3A10Z&ske=2024-05-15T01%3A30%3A10Z&sks=b&skv=2022-11-02&sv=2022-11-02&spr=https&se=2024-05-15T01%3A30%3A10Z&sr=b&sp=r&sig=vOQA3dKUuJdyAdRe7d%2FPUZNHj91fzL%2FGRDWsTO5%2BOuo%3D",
    "wallpapersden.com_blue-violet-minimal-gradient_7680x4320": "https://docserverpwaprodseau.blob.core.windows.net/61486d5b-017f-479f-8a47-174bd52dd6f4-1/resource/Assets0Images00014.jpg?skoid=58690ece-ec83-4ce2-9ce8-883d4d6a54ee&sktid=975f013f-7f24-47e8-a7d3-abc4752bf346&skt=2024-05-14T01%3A15%3A10Z&ske=2024-05-15T01%3A30%3A10Z&sks=b&skv=2022-11-02&sv=2022-11-02&spr=https&se=2024-05-15T01%3A30%3A10Z&sr=b&sp=r&sig=7qT927S4iPcm1ZtTjMgJj4R8OO1xOP7EF2yIzyBDybg%3D",
    "wearenotthesame-v0-amxhlh6ih5hc1": "https://docserverpwaprodseau.blob.core.windows.net/61486d5b-017f-479f-8a47-174bd52dd6f4-1/resource/Assets0Images00015.jpeg?skoid=58690ece-ec83-4ce2-9ce8-883d4d6a54ee&sktid=975f013f-7f24-47e8-a7d3-abc4752bf346&skt=2024-05-14T01%3A15%3A10Z&ske=2024-05-15T01%3A30%3A10Z&sks=b&skv=2022-11-02&sv=2022-11-02&spr=https&se=2024-05-15T01%3A30%3A10Z&sr=b&sp=r&sig=N1yBV8%2FiNBsg1IgE%2Fo%2BpT%2Bm0UpPTLop3dGtcmFqpSFk%3D"
  },
  "OldLogoFileName": "logo.jpg",
  "OrderComponentMetadata": {},
  "OrderComponentTemplate": {},
  "OrderDataSource": {
    "ComboBoxSample": 2,
    "CustomGallerySample": 3,
    "Office365Outlook": 0,
    "Office365Users": 1,
    "recipes": 4,
    "user_appliances": 5,
    "user_ingredients": 6,
    "user_logins": 7,
    "user_preferences": 8
  },
  "OrderGroupControls": {
    "Group2": {
      "Image1": 2,
      "Label10": 4,
      "Label8": 1,
      "Label9": 3,
      "Rectangle2": 0
    },
    "Group4": {
      "Container2": 0,
      "Icon1": 1,
      "Icon2": 2,
      "Icon3": 3
    },
    "Group4_1": {
      "Button1_10": 2,
      "Button1_11": 1,
      "Button1_9": 3,
      "Container2_3": 0,
      "Icon1_3": 4,
      "Icon2_3": 5,
      "Icon3_3": 6
    },
    "Group4_2": {
      "Container2_1": 0,
      "Icon1_1": 1,
      "Icon2_1": 2,
      "Icon3_1": 3
    },
    "Group4_3": {
      "Container2_2": 0,
      "Icon1_2": 1,
      "Icon2_2": 2,
      "Icon3_2": 3
    },
    "Group7": {
      "Button4": 10,
      "Button4_1": 12,
      "Button4_2": 11,
      "Button4_3": 16,
      "Circle1": 3,
      "Circle1_1": 6,
      "Circle1_2": 9,
      "Circle1_3": 15,
      "Label12": 2,
      "Label12_1": 5,
      "Label12_2": 8,
      "Label12_3": 14,
      "Rectangle3": 0,
      "Rectangle5": 1,
      "Rectangle5_1": 4,
      "Rectangle5_2": 7,
      "Rectangle5_3": 13
    },
    "Wheat": {
      "Button4_4": 3,
      "Circle1_4": 2,
      "Label12_4": 1,
      "Rectangle5_4": 0
    },
    "Wheat_1": {
      "Button4_5": 3,
      "Circle1_5": 2,
      "Label12_5": 1,
      "Rectangle5_5": 0
    }
  },
  "OrderPcfTemplate": {},
  "OrderTemplate": {},
  "OrderXMLTemplate": {
    "addMedia": 12,
    "button": 4,
    "checkbox": 7,
    "circle": 5,
    "combobox": 11,
    "datepicker": 10,
    "form": 8,
    "gallery": 13,
    "groupContainer": 6,
    "icon": 3,
    "image": 0,
    "label": 2,
    "rectangle": 1,
    "text": 9
  },
  "OverridablePropertiesEntry": {
    "8d4b12e1-8250-4eaf-863d-405bbb32f47b": {},
    "9771dc74-bce8-4b90-87e7-e57d8f02d4af": {},
    "AddAppliancesForm": {},
    "AddIngredientsForm": {},
    "AddPicture1": {},
    "App": {},
    "Appliance_Image_DataCard1": {},
    "Body1_1": {},
    "Button1_10": {},
    "Button1_11": {},
    "Button1_9": {},
    "Button2": {},
    "Button3": {},
    "Button3_1": {},
    "Button3_2": {},
    "Button4": {},
    "Button4_1": {},
    "Button4_2": {},
    "Button4_3": {},
    "Button4_4": {},
    "Button4_5": {},
    "Checkbox1": {},
    "Checkbox1_1": {},
    "Checkbox1_2": {},
    "Checkbox1_3": {},
    "Checkbox1_4": {},
    "Checkbox1_5": {},
    "Checkbox1_6": {},
    "Checkbox1_7": {},
    "Checkbox1_8": {},
    "Circle1": {},
    "Circle1_1": {},
    "Circle1_2": {},
    "Circle1_3": {},
    "Circle1_4": {},
    "Circle1_5": {},
    "Container1": {},
    "Container2": {},
    "Container2_1": {},
    "Container2_2": {},
    "Container2_3": {},
    "Container3": {},
    "Container4": {},
    "Container5": {},
    "Container6": {},
    "Container7": {},
    "Cooking Method(s)_DataCard1": {},
    "DataCardKey1": {},
    "DataCardKey2": {},
    "DataCardKey3": {},
    "DataCardKey6": {},
    "DataCardKey7": {},
    "DataCardKey8": {},
    "DataCardKey9": {},
    "DataCardValue1": {},
    "DataCardValue2": {},
    "DataCardValue6": {},
    "DataCardValue7": {},
    "DataCardValue8": {},
    "DataCardValue9": {},
    "EditForm1": {},
    "EditForm2": {},
    "ErrorMessage1": {},
    "ErrorMessage2": {},
    "ErrorMessage3": {},
    "ErrorMessage6": {},
    "ErrorMessage7": {},
    "ErrorMessage8": {},
    "ErrorMessage9": {},
    "Expiry_DataCard2": {},
    "Gallery1": {},
    "Gallery1_1": {},
    "Gallery2": {},
    "galleryTemplate1": {},
    "galleryTemplate1_1": {},
    "galleryTemplate2": {},
    "Group2": {},
    "Group4": {},
    "Group4_1": {},
    "Group4_2": {},
    "Group4_3": {},
    "Group7": {},
    "Home": {},
    "Host": {},
    "Icon1": {},
    "Icon1_1": {},
    "Icon1_2": {},
    "Icon1_3": {},
    "Icon2": {},
    "Icon2_1": {},
    "Icon2_2": {},
    "Icon2_3": {},
    "Icon3": {},
    "Icon3_1": {},
    "Icon3_2": {},
    "Icon3_3": {},
    "Icon4": {},
    "Icon5": {},
    "Icon6": {},
    "Icon7": {},
    "Icon8": {},
    "IconAccept1": {},
    "IconAccept2": {},
    "IconCancel1": {},
    "IconCancel2": {},
    "Image1": {},
    "Image10": {},
    "Image2": {},
    "Image5": {},
    "Image5_1": {},
    "Image9": {},
    "Kitchen": {},
    "Label1": {},
    "Label1_1": {},
    "Label1_2": {},
    "Label1_3": {},
    "Label1_4": {},
    "Label10": {},
    "Label11": {},
    "Label12": {},
    "Label12_1": {},
    "Label12_2": {},
    "Label12_3": {},
    "Label12_4": {},
    "Label12_5": {},
    "Label2": {},
    "Label2_1": {},
    "Label3": {},
    "Label4": {},
    "Label5": {},
    "Label6": {},
    "Label7": {},
    "Label7_1": {},
    "Label8": {},
    "Label9": {},
    "LblAppName1": {},
    "LblAppName2": {},
    "Login": {},
    "NextArrow1": {},
    "NextArrow3": {},
    "NextArrow4_1": {},
    "password_input": {},
    "Preference": {},
    "Quantity_DataCard2": {},
    "Rectangle1": {},
    "Rectangle2": {},
    "Rectangle3": {},
    "Rectangle4_1": {},
    "Rectangle5": {},
    "Rectangle5_1": {},
    "Rectangle5_2": {},
    "Rectangle5_3": {},
    "Rectangle5_4": {},
    "Rectangle5_5": {},
    "Rectangle6": {},
    "RectQuickActionBar1": {},
    "RectQuickActionBar2": {},
    "Separator1": {},
    "Separator3": {},
    "Separator4_1": {},
    "Settings": {},
    "StarVisible1": {},
    "StarVisible2": {},
    "StarVisible3": {},
    "StarVisible6": {},
    "StarVisible7": {},
    "StarVisible8": {},
    "StarVisible9": {},
    "Subtitle1": {},
    "Subtitle3_1": {},
    "Test_7F478737223C4B69": {},
    "Title_DataCard1": {},
    "Title_DataCard2": {},
    "Title1": {},
    "Title4_1": {},
    "Title7": {},
    "Units_DataCard2": {},
    "username_input": {},
    "Wheat": {},
    "Wheat_1": {}
  },
  "PCFDynamicSchemaForIRRetrievalEntry": {},
  "PCFTemplateEntry": {},
  "PublishOrderIndices": {
    "8d4b12e1-8250-4eaf-863d-405bbb32f47b": 180,
    "9771dc74-bce8-4b90-87e7-e57d8f02d4af": 179,
    "AddAppliancesForm": 1,
    "AddIngredientsForm": 23,
    "AddPicture1": 17,
    "App": 0,
    "Appliance_Image_DataCard1": 8,
    "Body1_1": 96,
    "Button1_10": 144,
    "Button1_11": 143,
    "Button1_9": 146,
    "Button2": 107,
    "Button3": 88,
    "Button3_1": 80,
    "Button3_2": 158,
    "Button4": 120,
    "Button4_1": 125,
    "Button4_2": 128,
    "Button4_3": 133,
    "Button4_4": 137,
    "Button4_5": 140,
    "Checkbox1": 168,
    "Checkbox1_1": 170,
    "Checkbox1_2": 171,
    "Checkbox1_3": 169,
    "Checkbox1_4": 172,
    "Checkbox1_5": 173,
    "Checkbox1_6": 175,
    "Checkbox1_7": 176,
    "Checkbox1_8": 177,
    "Circle1": 121,
    "Circle1_1": 124,
    "Circle1_2": 129,
    "Circle1_3": 132,
    "Circle1_4": 136,
    "Circle1_5": 141,
    "Container1": 99,
    "Container2": 55,
    "Container2_1": 75,
    "Container2_2": 159,
    "Container2_3": 142,
    "Container3": 73,
    "Container4": 71,
    "Container5": 156,
    "Container6": 157,
    "Container7": 54,
    "Cooking Method(s)_DataCard1": 9,
    "DataCardKey1": 11,
    "DataCardKey2": 15,
    "DataCardKey3": 20,
    "DataCardKey6": 34,
    "DataCardKey7": 38,
    "DataCardKey8": 42,
    "DataCardKey9": 46,
    "DataCardValue1": 12,
    "DataCardValue2": 21,
    "DataCardValue6": 35,
    "DataCardValue7": 39,
    "DataCardValue8": 43,
    "DataCardValue9": 47,
    "EditForm1": 6,
    "EditForm2": 28,
    "ErrorMessage1": 13,
    "ErrorMessage2": 18,
    "ErrorMessage3": 22,
    "ErrorMessage6": 36,
    "ErrorMessage7": 40,
    "ErrorMessage8": 44,
    "ErrorMessage9": 48,
    "Expiry_DataCard2": 30,
    "Gallery1": 60,
    "Gallery1_1": 89,
    "Gallery2": 81,
    "galleryTemplate1": 61,
    "galleryTemplate1_1": 90,
    "galleryTemplate2": 82,
    "Group2": 151,
    "Group4": 59,
    "Group4_1": 149,
    "Group4_2": 79,
    "Group4_3": 163,
    "Group7": 152,
    "Home": 51,
    "Host": 0,
    "Icon1": 58,
    "Icon1_1": 78,
    "Icon1_2": 162,
    "Icon1_3": 147,
    "Icon2": 56,
    "Icon2_1": 76,
    "Icon2_2": 160,
    "Icon2_3": 145,
    "Icon3": 57,
    "Icon3_1": 77,
    "Icon3_2": 161,
    "Icon3_3": 148,
    "Icon4": 104,
    "Icon5": 102,
    "Icon6": 105,
    "Icon7": 112,
    "Icon8": 95,
    "IconAccept1": 5,
    "IconAccept2": 27,
    "IconCancel1": 3,
    "IconCancel2": 25,
    "Image1": 113,
    "Image10": 16,
    "Image2": 63,
    "Image5": 100,
    "Image5_1": 109,
    "Image9": 84,
    "Kitchen": 68,
    "Label1": 52,
    "Label1_1": 53,
    "Label1_2": 155,
    "Label1_3": 69,
    "Label1_4": 70,
    "Label10": 115,
    "Label11": 116,
    "Label12": 119,
    "Label12_1": 123,
    "Label12_2": 127,
    "Label12_3": 131,
    "Label12_4": 135,
    "Label12_5": 139,
    "Label2": 74,
    "Label2_1": 72,
    "Label3": 164,
    "Label4": 106,
    "Label5": 165,
    "Label6": 166,
    "Label7": 167,
    "Label7_1": 174,
    "Label8": 111,
    "Label9": 114,
    "LblAppName1": 4,
    "LblAppName2": 26,
    "Login": 98,
    "NextArrow1": 66,
    "NextArrow3": 85,
    "NextArrow4_1": 92,
    "password_input": 103,
    "Preference": 108,
    "Quantity_DataCard2": 31,
    "Rectangle1": 62,
    "Rectangle2": 110,
    "Rectangle3": 117,
    "Rectangle4_1": 91,
    "Rectangle5": 118,
    "Rectangle5_1": 122,
    "Rectangle5_2": 126,
    "Rectangle5_3": 130,
    "Rectangle5_4": 134,
    "Rectangle5_5": 138,
    "Rectangle6": 83,
    "RectQuickActionBar1": 2,
    "RectQuickActionBar2": 24,
    "Separator1": 67,
    "Separator3": 87,
    "Separator4_1": 97,
    "Settings": 154,
    "StarVisible1": 10,
    "StarVisible2": 14,
    "StarVisible3": 19,
    "StarVisible6": 33,
    "StarVisible7": 37,
    "StarVisible8": 41,
    "StarVisible9": 45,
    "Subtitle1": 65,
    "Subtitle3_1": 94,
    "Test_7F478737223C4B69": 0,
    "Title_DataCard1": 7,
    "Title_DataCard2": 29,
    "Title1": 64,
    "Title4_1": 93,
    "Title7": 86,
    "Units_DataCard2": 32,
    "username_input": 101,
    "Wheat": 153,
    "Wheat_1": 150
  },
  "ResourcesJsonIndices": {
    "Image-615-6151019_white-rounded-rectangle-png-squircle-shape-transparent-png": 1,
    "Image-blank-profile-picture-973460_640": 2,
    "Image-image2706832": 3,
    "Image-image2706833": 4,
    "Image-image2706834": 5,
    "Image-image2706835": 6,
    "Image-image2706836": 7,
    "Image-image2706851": 8,
    "Image-image2706933": 9,
    "Image-image2706935": 10,
    "Image-image2706941": 11,
    "Image-png-clipart-computer-icons-rectangle-graphics-software-rounded-polygon-black-thumbnail": 12,
    "Image-SampleImage": 0,
    "Image-Screenshot 2024-05-12 122449": 13,
    "Image-wallpapersden.com_blue-violet-minimal-gradient_7680x4320": 14,
    "Image-wearenotthesame-v0-amxhlh6ih5hc1": 15
  },
  "RuleScreenIdWithoutScreen": {},
  "TemplateVersions": {},
  "VolatileProperties": {
    "AnalysisLoadTime": 1.6160414,
    "ControlCount": {
      "addMedia": 1,
      "button": 13,
      "checkbox": 9,
      "circle": 6,
      "combobox": 2,
      "datepicker": 1,
      "form": 2,
      "gallery": 3,
      "galleryTemplate": 3,
      "group": 8,
      "groupContainer": 10,
      "icon": 24,
      "image": 6,
      "label": 52,
      "rectangle": 16,
      "screen": 7,
      "TestCase": 1,
      "TestSuite": 1,
      "text": 5,
      "typedDataCard": 7
    },
    "DeserializationLoadTime": 3.9088701
  },
  "WasLocalDatabaseReferencesEmpty": true
}